jax_plugins/xla_cuda11/__init__.py
jax_plugins/xla_cuda11/version.py
jax_plugins/xla_cuda11/xla_cuda_plugin.so
jax_cuda11_pjrt-0.4.25.dist-info/METADATA
jax_cuda11_pjrt-0.4.25.dist-info/WHEEL
jax_cuda11_pjrt-0.4.25.dist-info/entry_points.txt
jax_cuda11_pjrt-0.4.25.dist-info/top_level.txt
jax_cuda11_pjrt-0.4.25.dist-info/RECORD
